{"entities":{"e4d1f157-a83c-48f2-8d87-44b42b61ebd1":{"enabled":true,"tags":[],"children":["a29bc433-6a07-4c63-b586-ca8fee2268de","360789c6-0f5f-4670-8fc3-1c18009e858f","d25c8ae3-2085-4325-99d8-8dc55027adf7","5c6c6a20-96a4-45fa-9ec6-7890ce804927","ec2db497-32ff-4d43-bdb4-b21f72e46489","c4754d00-aa12-4e86-b02c-13ff4ce66301","4695bc09-7ce9-4c0d-9447-50c6327aeeb6","546c85d8-24cf-4d51-97cc-76307663e3b7","64db6530-c177-42b1-ac26-c39b0cd32b5e","156ac1e5-aafa-4322-84ec-339abafd4735","6d1751fc-de7c-446f-abe5-b053648d8f62","0aaae155-ca50-4276-857a-202db9bccd16","ea695c71-d509-4583-a240-bf8854c40cba","c8dcf1cd-bccf-4f1c-8dcd-fd78f521b450","59c6f8ed-3fef-476e-9905-d243bc1c2a39","42eee07a-3dc1-4ee7-a647-83758f0418d1","ba11eb60-5105-4da5-8410-ddf02c29912f","8eda584d-6095-434d-9933-00ec41b8a4d2","4c98126a-7818-4071-abdb-6c4245baf53c","a3fda861-05c2-42a8-acf6-0593b7c3c1f9","b86316c4-ba1a-49c0-8b5b-716e316ae332","3915f040-d561-4d61-9968-e41e0d1f911d","ae5a3984-3b59-4a23-ae29-5c45a3dc3976"],"position":[0,0,0],"rotation":[0,0,0],"scale":[0.01,0.01,0.01],"resource_id":"e4d1f157-a83c-48f2-8d87-44b42b61ebd1","name":"RootNode","components":{},"parent":null},"a29bc433-6a07-4c63-b586-ca8fee2268de":{"enabled":true,"tags":[],"children":[],"position":[0,29.7,0],"rotation":[0,0,0],"scale":[1,1,1],"resource_id":"a29bc433-6a07-4c63-b586-ca8fee2268de","name":"Body","components":{"render":{"enabled":true,"type":"asset","asset":210474750,"materialAssets":[210474773],"layers":[0],"batchGroupId":null,"castShadows":true,"castShadowsLightmap":true,"receiveShadows":true,"lightmapped":false,"lightmapSizeMultiplier":1,"castShadowsLightMap":true,"lightMapped":false,"lightMapSizeMultiplier":1,"isStatic":false,"rootBone":null}},"parent":"e4d1f157-a83c-48f2-8d87-44b42b61ebd1"},"360789c6-0f5f-4670-8fc3-1c18009e858f":{"enabled":true,"tags":[],"children":[],"position":[0,29.7,0],"rotation":[0,0,0],"scale":[1,1,1],"resource_id":"360789c6-0f5f-4670-8fc3-1c18009e858f","name":"Window","components":{"render":{"enabled":true,"type":"asset","asset":210474751,"materialAssets":[210474777],"layers":[0],"batchGroupId":null,"castShadows":true,"castShadowsLightmap":true,"receiveShadows":true,"lightmapped":false,"lightmapSizeMultiplier":1,"castShadowsLightMap":true,"lightMapped":false,"lightMapSizeMultiplier":1,"isStatic":false,"rootBone":null}},"parent":"e4d1f157-a83c-48f2-8d87-44b42b61ebd1"},"d25c8ae3-2085-4325-99d8-8dc55027adf7":{"enabled":true,"tags":[],"children":[],"position":[0,95.8806,60.2055],"rotation":[0,0,0],"scale":[1,1,1],"resource_id":"d25c8ae3-2085-4325-99d8-8dc55027adf7","name":"Bonnet","components":{"render":{"enabled":true,"type":"asset","asset":210474718,"materialAssets":[210474771],"layers":[0],"batchGroupId":null,"castShadows":true,"castShadowsLightmap":true,"receiveShadows":true,"lightmapped":false,"lightmapSizeMultiplier":1,"castShadowsLightMap":true,"lightMapped":false,"lightMapSizeMultiplier":1,"isStatic":false,"rootBone":null}},"parent":"e4d1f157-a83c-48f2-8d87-44b42b61ebd1"},"5c6c6a20-96a4-45fa-9ec6-7890ce804927":{"enabled":true,"tags":[],"children":[],"position":[-51.9672,96.3754,49.3867],"rotation":[0,0,0],"scale":[1,1,1],"resource_id":"5c6c6a20-96a4-45fa-9ec6-7890ce804927","name":"RDoor","components":{"render":{"enabled":true,"type":"asset","asset":210474719,"materialAssets":[210474771],"layers":[0],"batchGroupId":null,"castShadows":true,"castShadowsLightmap":true,"receiveShadows":true,"lightmapped":false,"lightmapSizeMultiplier":1,"castShadowsLightMap":true,"lightMapped":false,"lightMapSizeMultiplier":1,"isStatic":false,"rootBone":null}},"parent":"e4d1f157-a83c-48f2-8d87-44b42b61ebd1"},"ec2db497-32ff-4d43-bdb4-b21f72e46489":{"enabled":true,"tags":[],"children":[],"position":[51.9672,96.3754,49.3867],"rotation":[0,0,0],"scale":[1,1,1],"resource_id":"ec2db497-32ff-4d43-bdb4-b21f72e46489","name":"LDoor","components":{"render":{"enabled":true,"type":"asset","asset":210474720,"materialAssets":[210474771],"layers":[0],"batchGroupId":null,"castShadows":true,"castShadowsLightmap":true,"receiveShadows":true,"lightmapped":false,"lightmapSizeMultiplier":1,"castShadowsLightMap":true,"lightMapped":false,"lightMapSizeMultiplier":1,"isStatic":false,"rootBone":null}},"parent":"e4d1f157-a83c-48f2-8d87-44b42b61ebd1"},"c4754d00-aa12-4e86-b02c-13ff4ce66301":{"enabled":true,"tags":[],"children":[],"position":[0,80.5,-126],"rotation":[5.7,0,0],"scale":[1,1,1],"resource_id":"c4754d00-aa12-4e86-b02c-13ff4ce66301","name":"Engine","components":{"render":{"enabled":true,"type":"asset","asset":210474721,"materialAssets":[210474776],"layers":[0],"batchGroupId":null,"castShadows":true,"castShadowsLightmap":true,"receiveShadows":true,"lightmapped":false,"lightmapSizeMultiplier":1,"castShadowsLightMap":true,"lightMapped":false,"lightMapSizeMultiplier":1,"isStatic":false,"rootBone":null}},"parent":"e4d1f157-a83c-48f2-8d87-44b42b61ebd1"},"4695bc09-7ce9-4c0d-9447-50c6327aeeb6":{"enabled":true,"tags":[],"children":[],"position":[29.8,81,-21.1],"rotation":[0,0,0],"scale":[1,1,1],"resource_id":"4695bc09-7ce9-4c0d-9447-50c6327aeeb6","name":"Driver","components":{"render":{"enabled":true,"type":"asset","asset":210474722,"materialAssets":[210474776],"layers":[0],"batchGroupId":null,"castShadows":true,"castShadowsLightmap":true,"receiveShadows":true,"lightmapped":false,"lightmapSizeMultiplier":1,"castShadowsLightMap":true,"lightMapped":false,"lightMapSizeMultiplier":1,"isStatic":false,"rootBone":null}},"parent":"e4d1f157-a83c-48f2-8d87-44b42b61ebd1"},"546c85d8-24cf-4d51-97cc-76307663e3b7":{"enabled":true,"tags":[],"children":[],"position":[-81,38.8502,120],"rotation":[0,0,0],"scale":[1,1,1],"resource_id":"546c85d8-24cf-4d51-97cc-76307663e3b7","name":"FR_Wheel","components":{"render":{"enabled":true,"type":"asset","asset":210474723,"materialAssets":[210474758],"layers":[0],"batchGroupId":null,"castShadows":true,"castShadowsLightmap":true,"receiveShadows":true,"lightmapped":false,"lightmapSizeMultiplier":1,"castShadowsLightMap":true,"lightMapped":false,"lightMapSizeMultiplier":1,"isStatic":false,"rootBone":null}},"parent":"e4d1f157-a83c-48f2-8d87-44b42b61ebd1"},"64db6530-c177-42b1-ac26-c39b0cd32b5e":{"enabled":true,"tags":[],"children":[],"position":[-35.962,77.9993,120],"rotation":[0,0,-40],"scale":[1,1,1],"resource_id":"64db6530-c177-42b1-ac26-c39b0cd32b5e","name":"FR_Spring","components":{"render":{"enabled":true,"type":"asset","asset":210474724,"materialAssets":[210474771],"layers":[0],"batchGroupId":null,"castShadows":true,"castShadowsLightmap":true,"receiveShadows":true,"lightmapped":false,"lightmapSizeMultiplier":1,"castShadowsLightMap":true,"lightMapped":false,"lightMapSizeMultiplier":1,"isStatic":false,"rootBone":null}},"parent":"e4d1f157-a83c-48f2-8d87-44b42b61ebd1"},"156ac1e5-aafa-4322-84ec-339abafd4735":{"enabled":true,"tags":[],"children":[],"position":[-20.749,37.411,120],"rotation":[0,0,0],"scale":[1,1,1],"resource_id":"156ac1e5-aafa-4322-84ec-339abafd4735","name":"FR_BotStrut","components":{"render":{"enabled":true,"type":"asset","asset":210474725,"materialAssets":[210474776],"layers":[0],"batchGroupId":null,"castShadows":true,"castShadowsLightmap":true,"receiveShadows":true,"lightmapped":false,"lightmapSizeMultiplier":1,"castShadowsLightMap":true,"lightMapped":false,"lightMapSizeMultiplier":1,"isStatic":false,"rootBone":null}},"parent":"e4d1f157-a83c-48f2-8d87-44b42b61ebd1"},"6d1751fc-de7c-446f-abe5-b053648d8f62":{"enabled":true,"tags":[],"children":[],"position":[-26.0387,51.6276,120],"rotation":[0,0,0],"scale":[1,1,1],"resource_id":"6d1751fc-de7c-446f-abe5-b053648d8f62","name":"FR_TopStrut","components":{"render":{"enabled":true,"type":"asset","asset":210474726,"materialAssets":[210474776],"layers":[0],"batchGroupId":null,"castShadows":true,"castShadowsLightmap":true,"receiveShadows":true,"lightmapped":false,"lightmapSizeMultiplier":1,"castShadowsLightMap":true,"lightMapped":false,"lightMapSizeMultiplier":1,"isStatic":false,"rootBone":null}},"parent":"e4d1f157-a83c-48f2-8d87-44b42b61ebd1"},"0aaae155-ca50-4276-857a-202db9bccd16":{"enabled":true,"tags":[],"children":[],"position":[-36,37.4,-120],"rotation":[0,0,0],"scale":[1,1,1],"resource_id":"0aaae155-ca50-4276-857a-202db9bccd16","name":"BR_BotStrut","components":{"render":{"enabled":true,"type":"asset","asset":210474727,"materialAssets":[210474776],"layers":[0],"batchGroupId":null,"castShadows":true,"castShadowsLightmap":true,"receiveShadows":true,"lightmapped":false,"lightmapSizeMultiplier":1,"castShadowsLightMap":true,"lightMapped":false,"lightMapSizeMultiplier":1,"isStatic":false,"rootBone":null}},"parent":"e4d1f157-a83c-48f2-8d87-44b42b61ebd1"},"ea695c71-d509-4583-a240-bf8854c40cba":{"enabled":true,"tags":[],"children":[],"position":[-36.6,51.6,-120],"rotation":[0,0,0],"scale":[1,1,1],"resource_id":"ea695c71-d509-4583-a240-bf8854c40cba","name":"BR_TopStrut","components":{"render":{"enabled":true,"type":"asset","asset":210474729,"materialAssets":[210474776],"layers":[0],"batchGroupId":null,"castShadows":true,"castShadowsLightmap":true,"receiveShadows":true,"lightmapped":false,"lightmapSizeMultiplier":1,"castShadowsLightMap":true,"lightMapped":false,"lightMapSizeMultiplier":1,"isStatic":false,"rootBone":null}},"parent":"e4d1f157-a83c-48f2-8d87-44b42b61ebd1"},"c8dcf1cd-bccf-4f1c-8dcd-fd78f521b450":{"enabled":true,"tags":[],"children":[],"position":[46.8,84,-120],"rotation":[0,0,26],"scale":[1,1,1],"resource_id":"c8dcf1cd-bccf-4f1c-8dcd-fd78f521b450","name":"BL_Spring","components":{"render":{"enabled":true,"type":"asset","asset":210474730,"materialAssets":[210474771],"layers":[0],"batchGroupId":null,"castShadows":true,"castShadowsLightmap":true,"receiveShadows":true,"lightmapped":false,"lightmapSizeMultiplier":1,"castShadowsLightMap":true,"lightMapped":false,"lightMapSizeMultiplier":1,"isStatic":false,"rootBone":null}},"parent":"e4d1f157-a83c-48f2-8d87-44b42b61ebd1"},"59c6f8ed-3fef-476e-9905-d243bc1c2a39":{"enabled":true,"tags":[],"children":[],"position":[20.7,37.4,120],"rotation":[0,0,0],"scale":[1,1,1],"resource_id":"59c6f8ed-3fef-476e-9905-d243bc1c2a39","name":"FL_BotStrut","components":{"render":{"enabled":true,"type":"asset","asset":210474731,"materialAssets":[210474776],"layers":[0],"batchGroupId":null,"castShadows":true,"castShadowsLightmap":true,"receiveShadows":true,"lightmapped":false,"lightmapSizeMultiplier":1,"castShadowsLightMap":true,"lightMapped":false,"lightMapSizeMultiplier":1,"isStatic":false,"rootBone":null}},"parent":"e4d1f157-a83c-48f2-8d87-44b42b61ebd1"},"42eee07a-3dc1-4ee7-a647-83758f0418d1":{"enabled":true,"tags":[],"children":[],"position":[26,51.6,120],"rotation":[0,0,0],"scale":[1,1,1],"resource_id":"42eee07a-3dc1-4ee7-a647-83758f0418d1","name":"FL_TopStrut","components":{"render":{"enabled":true,"type":"asset","asset":210474728,"materialAssets":[210474776],"layers":[0],"batchGroupId":null,"castShadows":true,"castShadowsLightmap":true,"receiveShadows":true,"lightmapped":false,"lightmapSizeMultiplier":1,"castShadowsLightMap":true,"lightMapped":false,"lightMapSizeMultiplier":1,"isStatic":false,"rootBone":null}},"parent":"e4d1f157-a83c-48f2-8d87-44b42b61ebd1"},"ba11eb60-5105-4da5-8410-ddf02c29912f":{"enabled":true,"tags":[],"children":[],"position":[36,37.4,-120],"rotation":[0,0,0],"scale":[1,1,1],"resource_id":"ba11eb60-5105-4da5-8410-ddf02c29912f","name":"BL_BotStrut","components":{"render":{"enabled":true,"type":"asset","asset":210474732,"materialAssets":[210474776],"layers":[0],"batchGroupId":null,"castShadows":true,"castShadowsLightmap":true,"receiveShadows":true,"lightmapped":false,"lightmapSizeMultiplier":1,"castShadowsLightMap":true,"lightMapped":false,"lightMapSizeMultiplier":1,"isStatic":false,"rootBone":null}},"parent":"e4d1f157-a83c-48f2-8d87-44b42b61ebd1"},"8eda584d-6095-434d-9933-00ec41b8a4d2":{"enabled":true,"tags":[],"children":[],"position":[36.6,51.6,-120],"rotation":[0,0,0],"scale":[1,1,1],"resource_id":"8eda584d-6095-434d-9933-00ec41b8a4d2","name":"BL_TopStrut","components":{"render":{"enabled":true,"type":"asset","asset":210474748,"materialAssets":[210474776],"layers":[0],"batchGroupId":null,"castShadows":true,"castShadowsLightmap":true,"receiveShadows":true,"lightmapped":false,"lightmapSizeMultiplier":1,"castShadowsLightMap":true,"lightMapped":false,"lightMapSizeMultiplier":1,"isStatic":false,"rootBone":null}},"parent":"e4d1f157-a83c-48f2-8d87-44b42b61ebd1"},"4c98126a-7818-4071-abdb-6c4245baf53c":{"enabled":true,"tags":[],"children":[],"position":[-81,38.8502,-120],"rotation":[0,0,0],"scale":[1,1,1],"resource_id":"4c98126a-7818-4071-abdb-6c4245baf53c","name":"BR_Wheel","components":{"render":{"enabled":true,"type":"asset","asset":210474733,"materialAssets":[210474758],"layers":[0],"batchGroupId":null,"castShadows":true,"castShadowsLightmap":true,"receiveShadows":true,"lightmapped":false,"lightmapSizeMultiplier":1,"castShadowsLightMap":true,"lightMapped":false,"lightMapSizeMultiplier":1,"isStatic":false,"rootBone":null}},"parent":"e4d1f157-a83c-48f2-8d87-44b42b61ebd1"},"a3fda861-05c2-42a8-acf6-0593b7c3c1f9":{"enabled":true,"tags":[],"children":[],"position":[-46.8,84,-120],"rotation":[0,0,-26],"scale":[1,1,1],"resource_id":"a3fda861-05c2-42a8-acf6-0593b7c3c1f9","name":"BR_Spring","components":{"render":{"enabled":true,"type":"asset","asset":210474734,"materialAssets":[210474771],"layers":[0],"batchGroupId":null,"castShadows":true,"castShadowsLightmap":true,"receiveShadows":true,"lightmapped":false,"lightmapSizeMultiplier":1,"castShadowsLightMap":true,"lightMapped":false,"lightMapSizeMultiplier":1,"isStatic":false,"rootBone":null}},"parent":"e4d1f157-a83c-48f2-8d87-44b42b61ebd1"},"b86316c4-ba1a-49c0-8b5b-716e316ae332":{"enabled":true,"tags":[],"children":[],"position":[36,78,120],"rotation":[0,0,40],"scale":[1,1,1],"resource_id":"b86316c4-ba1a-49c0-8b5b-716e316ae332","name":"FL_Spring","components":{"render":{"enabled":true,"type":"asset","asset":210474735,"materialAssets":[210474771],"layers":[0],"batchGroupId":null,"castShadows":true,"castShadowsLightmap":true,"receiveShadows":true,"lightmapped":false,"lightmapSizeMultiplier":1,"castShadowsLightMap":true,"lightMapped":false,"lightMapSizeMultiplier":1,"isStatic":false,"rootBone":null}},"parent":"e4d1f157-a83c-48f2-8d87-44b42b61ebd1"},"3915f040-d561-4d61-9968-e41e0d1f911d":{"enabled":true,"tags":[],"children":[],"position":[81,38.8502,120],"rotation":[0,0,0],"scale":[1,1,1],"resource_id":"3915f040-d561-4d61-9968-e41e0d1f911d","name":"FL_Wheel","components":{"render":{"enabled":true,"type":"asset","asset":210474737,"materialAssets":[210474758],"layers":[0],"batchGroupId":null,"castShadows":true,"castShadowsLightmap":true,"receiveShadows":true,"lightmapped":false,"lightmapSizeMultiplier":1,"castShadowsLightMap":true,"lightMapped":false,"lightMapSizeMultiplier":1,"isStatic":false,"rootBone":null}},"parent":"e4d1f157-a83c-48f2-8d87-44b42b61ebd1"},"ae5a3984-3b59-4a23-ae29-5c45a3dc3976":{"enabled":true,"tags":[],"children":[],"position":[81,38.8502,-120],"rotation":[0,0,0],"scale":[1,1,1],"resource_id":"ae5a3984-3b59-4a23-ae29-5c45a3dc3976","name":"BL_Wheel","components":{"render":{"enabled":true,"type":"asset","asset":210474739,"materialAssets":[210474758],"layers":[0],"batchGroupId":null,"castShadows":true,"castShadowsLightmap":true,"receiveShadows":true,"lightmapped":false,"lightmapSizeMultiplier":1,"castShadowsLightMap":true,"lightMapped":false,"lightMapSizeMultiplier":1,"isStatic":false,"rootBone":null}},"parent":"e4d1f157-a83c-48f2-8d87-44b42b61ebd1"}}}